Metadata-Version: 2.1
Name: peoples-payments
Version: 1.0.16
Summary: Peoples Payments API Python client
Home-page: https://www.peoplestrust.com/en/peoples-payment-solutions/team/
Author: Peoples Payments
Author-email: support@finixpayments.com
License: MIT License
Platform: UNKNOWN
Classifier: Intended Audience :: Developers
Classifier: License :: OSI Approved :: MIT License
Classifier: Programming Language :: Python
Classifier: Topic :: Software Development :: Libraries :: Python Modules
Provides-Extra: tests
